projects/project_6_led_blink/led_blink.v
///////////////////////////////////////////////////////////////////////////////
// Module: LED_Blink
// Purpose: Controls four LEDs, each blinking at a different rate
//
// Each LED has an independent counter. When the counter reaches its limit,
// the LED toggles and the counter resets. This creates a blinking effect at
// the rate determined by the counter limit and clock frequency.
//
// Parameters are used to make the design portable. For hardware synthesis,
// parameters are set to counts for 25 MHz clock. For testbench simulation,
// parameters are set to much smaller values to speed up testing.
///////////////////////////////////////////////////////////////////////////////

module LED_Blink (
  input i_Clk,
  output o_LED_1,
  output o_LED_2,
  output o_LED_3,
  output o_LED_4
);

  // Parameters set the toggle rate for each LED
  // For 25 MHz clock:
  //   10 Hz = 1,250,000 cycles
  //    5 Hz = 2,500,000 cycles
  //    2 Hz = 6,250,000 cycles
  //    1 Hz = 12,500,000 cycles
  parameter g_COUNT_10HZ = 1250000;
  parameter g_COUNT_5HZ  = 2500000;
  parameter g_COUNT_2HZ  = 6250000;
  parameter g_COUNT_1HZ  = 12500000;

  reg r_LED_1 = 1'b0;
  reg r_LED_2 = 1'b0;
  reg r_LED_3 = 1'b0;
  reg r_LED_4 = 1'b0;

  reg [24:0] r_Count_1 = 25'b0;  // Counter for LED 1 (10 Hz)
  reg [24:0] r_Count_2 = 25'b0;  // Counter for LED 2 (5 Hz)
  reg [24:0] r_Count_3 = 25'b0;  // Counter for LED 3 (2 Hz)
  reg [24:0] r_Count_4 = 25'b0;  // Counter for LED 4 (1 Hz)

  // LED 1: 10 Hz
  always @(posedge i_Clk)
  begin
    if (r_Count_1 == g_COUNT_10HZ)
    begin
      r_LED_1 <= ~r_LED_1;
      r_Count_1 <= 25'b0;
    end
    else
      r_Count_1 <= r_Count_1 + 1;
  end

  // LED 2: 5 Hz
  always @(posedge i_Clk)
  begin
    if (r_Count_2 == g_COUNT_5HZ)
    begin
      r_LED_2 <= ~r_LED_2;
      r_Count_2 <= 25'b0;
    end
    else
      r_Count_2 <= r_Count_2 + 1;
  end

  // LED 3: 2 Hz
  always @(posedge i_Clk)
  begin
    if (r_Count_3 == g_COUNT_2HZ)
    begin
      r_LED_3 <= ~r_LED_3;
      r_Count_3 <= 25'b0;
    end
    else
      r_Count_3 <= r_Count_3 + 1;
  end

  // LED 4: 1 Hz
  always @(posedge i_Clk)
  begin
    if (r_Count_4 == g_COUNT_1HZ)
    begin
      r_LED_4 <= ~r_LED_4;
      r_Count_4 <= 25'b0;
    end
    else
      r_Count_4 <= r_Count_4 + 1;
  end

  assign o_LED_1 = r_LED_1;
  assign o_LED_2 = r_LED_2;
  assign o_LED_3 = r_LED_3;
  assign o_LED_4 = r_LED_4;

endmodule

projects/project_6_led_blink/led_blink_tb.v
///////////////////////////////////////////////////////////////////////////////
// Testbench: LED_Blink_TB
// Purpose: Simulate LED_Blink module with fast-running parameters
//
// This testbench generates a clock, instantiates the LED_Blink module with
// small counter parameters (to speed up simulation), and monitors the outputs.
// The waveforms are dumped to a VCD file for inspection.
//
// Parameters are set much smaller than hardware values to make simulation fast:
//   LED 1 (10 Hz simulation): toggles every 10 cycles
//   LED 2 (5 Hz simulation):  toggles every 20 cycles
//   LED 3 (2 Hz simulation):  toggles every 40 cycles
//   LED 4 (1 Hz simulation):  toggles every 80 cycles
///////////////////////////////////////////////////////////////////////////////

`timescale 1ns / 1ps

module LED_Blink_TB;

  // Simulation clock: 25 MHz = 40 ns period
  // We'll use 1 ns units, so 40 time units per clock cycle
  localparam CLK_PERIOD = 40;

  reg r_Clk = 1'b0;
  wire w_LED_1;
  wire w_LED_2;
  wire w_LED_3;
  wire w_LED_4;

  // Generate a 25 MHz clock
  // This is simulation-only code (non-synthesizable)
  always #(CLK_PERIOD/2) r_Clk <= ~r_Clk;

  // Instantiate LED_Blink with small parameters for fast simulation
  LED_Blink #(
    .g_COUNT_10HZ(10),   // Toggle LED 1 every 10 cycles
    .g_COUNT_5HZ(20),    // Toggle LED 2 every 20 cycles
    .g_COUNT_2HZ(40),    // Toggle LED 3 every 40 cycles
    .g_COUNT_1HZ(80)     // Toggle LED 4 every 80 cycles
  ) LED_Blink_UUT (
    .i_Clk(r_Clk),
    .o_LED_1(w_LED_1),
    .o_LED_2(w_LED_2),
    .o_LED_3(w_LED_3),
    .o_LED_4(w_LED_4)
  );

  // Simulation-only code: initialize, dump waveforms, and run
  initial
  begin
    // Dump waveforms to VCD file for viewing in gtkwave
    $dumpfile("led_blink.vcd");
    $dumpvars(0, LED_Blink_TB);

    // Run simulation for 2000 time units (50 clock cycles at 40ns/cycle)
    // This is enough to see all LEDs toggle at least once
    #2000 $finish;
  end

endmodule

projects/project_6_led_blink/sim/led_blink.vcd
$date
	Wed Feb  4 15:25:16 2026
$end
$version
	Icarus Verilog
$end
$timescale
	1ps
$end
$scope module LED_Blink_TB $end
$var wire 1 ! w_LED_4 $end
$var wire 1 " w_LED_3 $end
$var wire 1 # w_LED_2 $end
$var wire 1 $ w_LED_1 $end
$var parameter 32 % CLK_PERIOD $end
$var reg 1 & r_Clk $end
$scope module LED_Blink_UUT $end
$var wire 1 & i_Clk $end
$var wire 1 $ o_LED_1 $end
$var wire 1 # o_LED_2 $end
$var wire 1 " o_LED_3 $end
$var wire 1 ! o_LED_4 $end
$var parameter 32 ' g_COUNT_10HZ $end
$var parameter 32 ( g_COUNT_1HZ $end
$var parameter 32 ) g_COUNT_2HZ $end
$var parameter 32 * g_COUNT_5HZ $end
$var reg 25 + r_Count_1 [24:0] $end
$var reg 25 , r_Count_2 [24:0] $end
$var reg 25 - r_Count_3 [24:0] $end
$var reg 25 . r_Count_4 [24:0] $end
$var reg 1 / r_LED_1 $end
$var reg 1 0 r_LED_2 $end
$var reg 1 1 r_LED_3 $end
$var reg 1 2 r_LED_4 $end
$upscope $end
$upscope $end
$enddefinitions $end
$comment Show the parameter values. $end
$dumpall
b10100 *
b101000 )
b1010000 (
b1010 '
b101000 %
$end
#0
$dumpvars
02
01
00
0/
b0 .
b0 -
b0 ,
b0 +
0&
0$
0#
0"
0!
$end
#20000
b1 +
b1 ,
b1 -
b1 .
1&
#40000
0&
#60000
b10 .
b10 -
b10 ,
b10 +
1&
#80000
0&
#100000
b11 +
b11 ,
b11 -
b11 .
1&
#120000
0&
#140000
b100 .
b100 -
b100 ,
b100 +
1&
#160000
0&
#180000
b101 +
b101 ,
b101 -
b101 .
1&
#200000
0&
#220000
b110 .
b110 -
b110 ,
b110 +
1&
#240000
0&
#260000
b111 +
b111 ,
b111 -
b111 .
1&
#280000
0&
#300000
b1000 .
b1000 -
b1000 ,
b1000 +
1&
#320000
0&
#340000
b1001 +
b1001 ,
b1001 -
b1001 .
1&
#360000
0&
#380000
b1010 .
b1010 -
b1010 ,
b1010 +
1&
#400000
0&
#420000
b0 +
1$
1/
b1011 ,
b1011 -
b1011 .
1&
#440000
0&
#460000
b1100 .
b1100 -
b1100 ,
b1 +
1&
#480000
0&
#500000
b10 +
b1101 ,
b1101 -
b1101 .
1&
#520000
0&
#540000
b1110 .
b1110 -
b1110 ,
b11 +
1&
#560000
0&
#580000
b100 +
b1111 ,
b1111 -
b1111 .
1&
#600000
0&
#620000
b10000 .
b10000 -
b10000 ,
b101 +
1&
#640000
0&
#660000
b110 +
b10001 ,
b10001 -
b10001 .
1&
#680000
0&
#700000
b10010 .
b10010 -
b10010 ,
b111 +
1&
#720000
0&
#740000
b1000 +
b10011 ,
b10011 -
b10011 .
1&
#760000
0&
#780000
b10100 .
b10100 -
b10100 ,
b1001 +
1&
#800000
0&
#820000
b1010 +
b0 ,
1#
10
b10101 -
b10101 .
1&
#840000
0&
#860000
b10110 .
b10110 -
b1 ,
b0 +
0$
0/
1&
#880000
0&
#900000
b1 +
b10 ,
b10111 -
b10111 .
1&
#920000
0&
#940000
b11000 .
b11000 -
b11 ,
b10 +
1&
#960000
0&
#980000
b11 +
b100 ,
b11001 -
b11001 .
1&
#1000000
0&
#1020000
b11010 .
b11010 -
b101 ,
b100 +
1&
#1040000
0&
#1060000
b101 +
b110 ,
b11011 -
b11011 .
1&
#1080000
0&
#1100000
b11100 .
b11100 -
b111 ,
b110 +
1&
#1120000
0&
#1140000
b111 +
b1000 ,
b11101 -
b11101 .
1&
#1160000
0&
#1180000
b11110 .
b11110 -
b1001 ,
b1000 +
1&
#1200000
0&
#1220000
b1001 +
b1010 ,
b11111 -
b11111 .
1&
#1240000
0&
#1260000
b100000 .
b100000 -
b1011 ,
b1010 +
1&
#1280000
0&
#1300000
b0 +
1$
1/
b1100 ,
b100001 -
b100001 .
1&
#1320000
0&
#1340000
b100010 .
b100010 -
b1101 ,
b1 +
1&
#1360000
0&
#1380000
b10 +
b1110 ,
b100011 -
b100011 .
1&
#1400000
0&
#1420000
b100100 .
b100100 -
b1111 ,
b11 +
1&
#1440000
0&
#1460000
b100 +
b10000 ,
b100101 -
b100101 .
1&
#1480000
0&
#1500000
b100110 .
b100110 -
b10001 ,
b101 +
1&
#1520000
0&
#1540000
b110 +
b10010 ,
b100111 -
b100111 .
1&
#1560000
0&
#1580000
b101000 .
b101000 -
b10011 ,
b111 +
1&
#1600000
0&
#1620000
b1000 +
b10100 ,
b0 -
1"
11
b101001 .
1&
#1640000
0&
#1660000
b101010 .
b1 -
b0 ,
0#
00
b1001 +
1&
#1680000
0&
#1700000
b1010 +
b1 ,
b10 -
b101011 .
1&
#1720000
0&
#1740000
b101100 .
b11 -
b10 ,
b0 +
0$
0/
1&
#1760000
0&
#1780000
b1 +
b11 ,
b100 -
b101101 .
1&
#1800000
0&
#1820000
b101110 .
b101 -
b100 ,
b10 +
1&
#1840000
0&
#1860000
b11 +
b101 ,
b110 -
b101111 .
1&
#1880000
0&
#1900000
b110000 .
b111 -
b110 ,
b100 +
1&
#1920000
0&
#1940000
b101 +
b111 ,
b1000 -
b110001 .
1&
#1960000
0&
#1980000
b110010 .
b1001 -
b1000 ,
b110 +
1&
